weather_cli_liuxq/__init__.py
weather_cli_liuxq/main.py
weather_cli_liuxq/天气返回结果.json
weather_cli_liuxq-0.2.0.dist-info/entry_points.txt
weather_cli_liuxq-0.2.0.dist-info/METADATA
weather_cli_liuxq-0.2.0.dist-info/WHEEL
weather_cli_liuxq-0.2.0.dist-info/RECORD
