Metadata-Version: 2.3
Name: weather-cli-liuxq
Version: 0.2.0
Summary: A simple CLI tool to check weather
License: MIT
Author: xiangqian19831224@126.com
Requires-Python: >=3.12.9,<4.0.0
Classifier: License :: OSI Approved :: MIT License
Classifier: Programming Language :: Python :: 3
Classifier: Programming Language :: Python :: 3.13
Requires-Dist: click (>=8.1.3,<9.0.0)
Requires-Dist: requests (>=2.28.1,<3.0.0)
